{
  "summary": {
    "instance": "r1_10_5",
    "family": "R1",
    "algorithm": "BIH",
    "vehicles": 98,
    "distance": 79890.3658,
    "runtime": 16.5416,
    "feasible": true,
    "served": 1000,
    "customers": 1000,
    "seed": ""
  },
  "routes": [
    [
      123,
      949,
      825,
      216,
      969,
      207,
      822,
      130,
      342,
      531,
      266,
      233
    ],
    [
      64,
      417,
      154,
      115,
      268,
      326,
      974,
      36,
      378,
      975,
      414,
      20,
      989
    ],
    [
      410,
      786,
      364,
      534,
      999,
      701,
      39,
      252,
      441,
      354,
      938,
      385,
      895
    ],
    [
      677,
      418,
      167,
      886,
      566,
      571,
      759,
      285,
      23,
      349
    ],
    [
      929,
      294,
      550,
      280,
      124,
      228,
      420,
      469,
      750,
      730
    ],
    [
      752,
      936,
      620,
      684,
      600,
      49,
      587,
      282,
      284,
      768,
      177,
      274,
      919
    ],
    [
      573,
      222,
      791,
      275,
      552,
      31,
      158,
      30,
      529,
      665,
      356,
      614
    ],
    [
      881,
      511,
      229,
      25,
      490,
      913,
      431,
      951,
      174,
      480,
      118,
      662
    ],
    [
      953,
      187,
      892,
      535,
      17,
      221,
      952,
      55,
      311,
      823
    ],
    [
      582,
      496,
      263,
      324,
      211,
      57,
      520,
      961,
      32,
      769
    ],
    [
      667,
      155,
      402,
      71,
      307,
      801,
      503,
      316,
      604,
      200,
      27,
      990,
      603
    ],
    [
      593,
      190,
      717,
      843,
      574,
      982,
      121,
      468,
      659,
      698,
      739,
      836
    ],
    [
      808,
      243,
      379,
      977,
      504,
      958,
      375,
      145,
      393,
      338,
      855
    ],
    [
      80,
      875,
      579,
      419,
      405,
      287,
      806,
      594,
      6,
      75,
      421
    ],
    [
      652,
      434,
      624,
      271,
      660,
      978,
      359,
      467,
      76,
      809
    ],
    [
      879,
      920,
      727,
      334,
      749,
      34,
      146,
      191,
      217,
      381,
      693,
      436,
      369
    ],
    [
      304,
      557,
      803,
      438,
      906,
      219,
      347,
      215,
      735,
      861,
      716,
      391
    ],
    [
      628,
      488,
      134,
      279,
      577,
      483,
      387,
      942,
      383
    ],
    [
      139,
      46,
      818,
      193,
      605,
      538,
      598,
      149,
      546,
      195,
      602,
      288
    ],
    [
      305,
      113,
      902,
      52,
      48,
      882,
      135,
      382,
      16,
      3
    ],
    [
      14,
      91,
      774,
      793,
      37,
      720,
      232,
      241,
      668,
      314,
      317,
      561,
      83
    ],
    [
      249,
      50,
      779,
      439,
      327,
      293,
      545,
      413,
      907,
      85,
      370
    ],
    [
      358,
      533,
      757,
      776,
      11,
      352,
      470,
      261,
      466,
      175,
      7
    ],
    [
      544,
      640,
      964,
      507,
      227,
      784,
      245,
      653,
      295,
      968,
      580,
      465,
      270,
      601
    ],
    [
      725,
      988,
      100,
      109,
      397,
      399,
      711,
      562,
      648,
      168
    ],
    [
      754,
      816,
      737,
      367,
      742,
      681,
      59,
      859,
      688,
      670,
      481
    ],
    [
      448,
      846,
      388,
      896,
      556,
      715,
      240,
      795,
      162,
      398,
      472,
      993
    ],
    [
      198,
      269,
      764,
      736,
      922,
      734,
      196,
      592,
      8
    ],
    [
      848,
      903,
      128,
      910,
      814,
      950,
      954,
      912,
      874,
      789,
      828,
      40
    ],
    [
      58,
      719,
      657,
      493,
      583,
      258,
      813,
      491,
      376,
      131,
      709
    ],
    [
      337,
      979,
      248,
      341,
      315,
      588,
      179,
      197,
      591,
      832,
      231
    ],
    [
      702,
      691,
      194,
      98,
      329,
      564,
      542,
      815,
      366,
      137,
      1,
      940
    ],
    [
      308,
      136,
      203,
      946,
      432,
      178,
      878,
      24,
      224,
      567,
      837,
      850
    ],
    [
      597,
      453,
      208,
      663,
      518,
      596,
      777,
      424,
      205,
      551,
      88
    ],
    [
      152,
      631,
      78,
      783,
      760,
      475,
      939,
      554,
      678,
      639,
      560,
      506,
      255
    ],
    [
      289,
      838,
      608,
      45,
      446,
      157,
      867,
      416,
      707,
      92,
      452
    ],
    [
      477,
      558,
      642,
      184,
      576,
      360,
      689,
      674,
      780,
      456
    ],
    [
      29,
      107,
      210,
      111,
      740,
      627,
      492,
      242,
      143,
      428,
      147
    ],
    [
      872,
      536,
      188,
      991,
      812,
      756,
      512,
      510,
      676,
      348
    ],
    [
      1000,
      637,
      409,
      442,
      220,
      972,
      437,
      12,
      840,
      619
    ],
    [
      692,
      339,
      273,
      984,
      508,
      169,
      797,
      705,
      5,
      44,
      933,
      682,
      310
    ],
    [
      276,
      763,
      644,
      94,
      868,
      67,
      125,
      568,
      422,
      357
    ],
    [
      995,
      180,
      236,
      523,
      578,
      722,
      19,
      649,
      996,
      831
    ],
    [
      462,
      738,
      312,
      959,
      350,
      685,
      647,
      525,
      331,
      733,
      392
    ],
    [
      230,
      292,
      458,
      368,
      226,
      41,
      246,
      666,
      443,
      864,
      291,
      13
    ],
    [
      86,
      345,
      401,
      476,
      484,
      251,
      880,
      380,
      171,
      238,
      926,
      539
    ],
    [
      73,
      841,
      395,
      548,
      425,
      102,
      451,
      353,
      346,
      272,
      450,
      445
    ],
    [
      835,
      732,
      454,
      778,
      181,
      766,
      332,
      847,
      643,
      362,
      865
    ],
    [
      679,
      54,
      575,
      870,
      464,
      351,
      839,
      494,
      344,
      889
    ],
    [
      675,
      502,
      403,
      683,
      930,
      309,
      429,
      857,
      798,
      976,
      514,
      747
    ],
    [
      858,
      654,
      156,
      335,
      956,
      153,
      871,
      661,
      90,
      172
    ],
    [
      885,
      934,
      765,
      296,
      225,
      298,
      807,
      62,
      151,
      966,
      69,
      336,
      166
    ],
    [
      928,
      250,
      714,
      509,
      343,
      43,
      186,
      72,
      570,
      810,
      883
    ],
    [
      931,
      599,
      947,
      482,
      962,
      303,
      638,
      609,
      2,
      521,
      214
    ],
    [
      908,
      457,
      669,
      897,
      856,
      724,
      33,
      259,
      325,
      923,
      981
    ],
    [
      849,
      555,
      164,
      672,
      994,
      869,
      4,
      826,
      119,
      887,
      301
    ],
    [
      447,
      680,
      473,
      904,
      300,
      170,
      406,
      935,
      955,
      987,
      163,
      633
    ],
    [
      160,
      553,
      120,
      585,
      543,
      426,
      824,
      390,
      333,
      430
    ],
    [
      905,
      199,
      234,
      563,
      863,
      498,
      884,
      10,
      81,
      805,
      519
    ],
    [
      696,
      899,
      374,
      440,
      412,
      526,
      321,
      183,
      909,
      340,
      851,
      474
    ],
    [
      433,
      95,
      731,
      595,
      9,
      363,
      615,
      192,
      237
    ],
    [
      26,
      944,
      629,
      748,
      495,
      265,
      829,
      427,
      623,
      636,
      980
    ],
    [
      700,
      901,
      161,
      817,
      460,
      641,
      404,
      22,
      830,
      945,
      528
    ],
    [
      983,
      590,
      924,
      973,
      497,
      524,
      355,
      833,
      646,
      584
    ],
    [
      66,
      708,
      365,
      411,
      396,
      785,
      745,
      286,
      56,
      782
    ],
    [
      617,
      38,
      126,
      891,
      862,
      852,
      998,
      900,
      479,
      925,
      97,
      408,
      84
    ],
    [
      361,
      140,
      963,
      781,
      400,
      47,
      159,
      827,
      771,
      957,
      612,
      283
    ],
    [
      960,
      209,
      133,
      389,
      150,
      690,
      42,
      888,
      860,
      549
    ],
    [
      655,
      890,
      515,
      937,
      373,
      206,
      99,
      522,
      671,
      626
    ],
    [
      645,
      914,
      103,
      189,
      821,
      415,
      79,
      985,
      63,
      699
    ],
    [
      873,
      992,
      622,
      127,
      132,
      500,
      513,
      761,
      112,
      244
    ],
    [
      746,
      758,
      755,
      471,
      114,
      505,
      658,
      572,
      318
    ],
    [
      463,
      876,
      116,
      70,
      611,
      322,
      204,
      772,
      565,
      485
    ],
    [
      394,
      212,
      744,
      444,
      917,
      18,
      129,
      613,
      87,
      767,
      277
    ],
    [
      262,
      435,
      971,
      686,
      787,
      728,
      104,
      794,
      319
    ],
    [
      260,
      165,
      185,
      330,
      948,
      842,
      499,
      921,
      997
    ],
    [
      77,
      581,
      811,
      328,
      723,
      792,
      915,
      15,
      423,
      918,
      323
    ],
    [
      893,
      710,
      96,
      799,
      540,
      741,
      93,
      60,
      530,
      916
    ],
    [
      820,
      804,
      773,
      965,
      256,
      176,
      941,
      108,
      894,
      267,
      297
    ],
    [
      21,
      986,
      967,
      713,
      407,
      65,
      142,
      877
    ],
    [
      74,
      712,
      223,
      635,
      694,
      278
    ],
    [
      122,
      138,
      148,
      386,
      788,
      290,
      625,
      51,
      516,
      729,
      796
    ],
    [
      656,
      306,
      35,
      607,
      630,
      182,
      569,
      834,
      501
    ],
    [
      606,
      616,
      377,
      770,
      547,
      586,
      532
    ],
    [
      487,
      695,
      89,
      372,
      202,
      621,
      537,
      320,
      589,
      541
    ],
    [
      932,
      718,
      517,
      651,
      853,
      302,
      371,
      762,
      664,
      264
    ],
    [
      673,
      703,
      313,
      254,
      449,
      800,
      281,
      144
    ],
    [
      697,
      704,
      459,
      943,
      618,
      239,
      384,
      253
    ],
    [
      486,
      706,
      650,
      218,
      105,
      61,
      101,
      845
    ],
    [
      819,
      53,
      634,
      82,
      173,
      106,
      632
    ],
    [
      117,
      489,
      844,
      753,
      721,
      898,
      687,
      478
    ],
    [
      775,
      299,
      235,
      461,
      455
    ],
    [
      790,
      28,
      751,
      527
    ],
    [
      201,
      802,
      257,
      970
    ],
    [
      854,
      927,
      68,
      610
    ],
    [
      911,
      141,
      743,
      559
    ],
    [
      726,
      213
    ],
    [
      110,
      247,
      866
    ]
  ]
}